artefacts_copava/__init__.py
artefacts_copava/constants.py
artefacts_copava/parsing.py
artefacts_copava/schemas.py
artefacts_copava/validating.py
artefacts_copava/version.py
artefacts_copava-0.1.15.dist-info/licenses/LICENSE
artefacts_copava-0.1.15.dist-info/METADATA
artefacts_copava-0.1.15.dist-info/WHEEL
artefacts_copava-0.1.15.dist-info/top_level.txt
artefacts_copava-0.1.15.dist-info/RECORD
